analytical/__init__.py
analytical/models.py
analytical/utils.py
analytical/templatetags/__init__.py
analytical/templatetags/analytical.py
analytical/templatetags/chartbeat.py
analytical/templatetags/clickmap.py
analytical/templatetags/clicky.py
analytical/templatetags/crazy_egg.py
analytical/templatetags/facebook_pixel.py
analytical/templatetags/gauges.py
analytical/templatetags/google_analytics.py
analytical/templatetags/google_analytics_gtag.py
analytical/templatetags/google_analytics_js.py
analytical/templatetags/gosquared.py
analytical/templatetags/hotjar.py
analytical/templatetags/hubspot.py
analytical/templatetags/intercom.py
analytical/templatetags/kiss_insights.py
analytical/templatetags/kiss_metrics.py
analytical/templatetags/luckyorange.py
analytical/templatetags/matomo.py
analytical/templatetags/mixpanel.py
analytical/templatetags/olark.py
analytical/templatetags/optimizely.py
analytical/templatetags/performable.py
analytical/templatetags/piwik.py
analytical/templatetags/rating_mailru.py
analytical/templatetags/snapengage.py
analytical/templatetags/spring_metrics.py
analytical/templatetags/uservoice.py
analytical/templatetags/woopra.py
analytical/templatetags/yandex_metrica.py
django_analytical-3.0.0.dist-info/AUTHORS.rst
django_analytical-3.0.0.dist-info/LICENSE.txt
django_analytical-3.0.0.dist-info/METADATA
django_analytical-3.0.0.dist-info/WHEEL
django_analytical-3.0.0.dist-info/top_level.txt
django_analytical-3.0.0.dist-info/RECORD
