Metadata-Version: 2.1
Name: django-analytical
Version: 3.0.0
Summary: Analytics service integration for Django projects
Home-page: https://github.com/jazzband/django-analytical
Author: Joost Cassee
Author-email: joost@cassee.net
License: MIT
Download-URL: https://github.com/jazzband/django-analytical/archive/master.zip
Project-URL: Documentation, https://django-analytical.readthedocs.io/
Keywords: django,analytics
Platform: any
Classifier: Development Status :: 5 - Production/Stable
Classifier: Environment :: Web Environment
Classifier: Framework :: Django
Classifier: Framework :: Django :: 2.2
Classifier: Framework :: Django :: 3.0
Classifier: Framework :: Django :: 3.1
Classifier: Intended Audience :: Developers
Classifier: License :: OSI Approved :: MIT License
Classifier: Operating System :: OS Independent
Classifier: Programming Language :: Python
Classifier: Programming Language :: Python :: 3
Classifier: Programming Language :: Python :: 3.6
Classifier: Programming Language :: Python :: 3.7
Classifier: Programming Language :: Python :: 3.8
Classifier: Programming Language :: Python :: 3.9
Classifier: Topic :: Internet :: WWW/HTTP
Classifier: Topic :: Software Development :: Libraries :: Python Modules
Requires-Python: >=3.6
